[
    {
        "Datum": "27.03.",
        "Symbol": "$SKINNY",
        "MCAP_at_Call": "281K",
        "Link": "https://dexscreener.com/solana/j1bwvcmek1r7z7r21usghu8vfywpbcs9dejgwjeweze",
        "Aktuelles_MCAP": "357K",
        "X_Factor": "1.3X",
        "PL_Percent": "27%",
        "PL_Dollar": "2.70$",
        "Invest": "10"
    },
    {
        "Datum": "27.03.",
        "Symbol": "$ragebait",
        "MCAP_at_Call": "101K",
        "Link": "https://dexscreener.com/solana/g8bj99s8dmp9cac3uhm5t9tycjh83waj3ppqcekjueif",
        "Aktuelles_MCAP": "65K",
        "X_Factor": "0.6X",
        "PL_Percent": "-36%",
        "PL_Dollar": "-3.56$",
        "Invest": "10"
    },
    {
        "Datum": "27.03.",
        "Symbol": "$REVS",
        "MCAP_at_Call": "817K",
        "Link": "9VxExA1iRPbuLLdSJ2rB3nyBxsyLReT4aqzZBMaBaY1p",
        "Aktuelles_MCAP": "833K",
        "X_Factor": "1.0X",
        "PL_Percent": "2%",
        "PL_Dollar": "0.20$",
        "Invest": "10"
    },
    {
        "Datum": "27.03.",
        "Symbol": "$AuraFarm",
        "MCAP_at_Call": "519K",
        "Link": "4rwPNRSFgcS7EGphFdX7VwXuhjZGxph7gYyb7Zp2pump",
        "Aktuelles_MCAP": "615K",
        "X_Factor": "1.2X",
        "PL_Percent": "18%",
        "PL_Dollar": "1.85$",
        "Invest": "10"
    },
    {
        "Datum": "27.03.",
        "Symbol": "$BONECOIN",
        "MCAP_at_Call": "952K",
        "Link": "BjCmA9ZYwJ1BwusMGaSxe4pgaa9gfXTtdyX27NYEpump",
        "Aktuelles_MCAP": "1.1M",
        "X_Factor": "1.2X",
        "PL_Percent": "16%",
        "PL_Dollar": "1.55$",
        "Invest": "10"
    },
    {
        "Datum": "27.03.",
        "Symbol": "$elegante",
        "MCAP_at_Call": "321K",
        "Link": "AhbrHSXQk8bvWyJbwUnF78733Ym5wtssViJ98jyzpump",
        "Aktuelles_MCAP": "303K",
        "X_Factor": "0.9X",
        "PL_Percent": "-6%",
        "PL_Dollar": "-0.56$",
        "Invest": "10"
    },
    {
        "Datum": "27.03.",
        "Symbol": "$Pumpswap ",
        "MCAP_at_Call": "179K",
        "Link": "https://dexscreener.com/solana/fdtu6w24k2iyw9ce9nstyvsmsgjxj2hhrtkkc2xftxsl",
        "Aktuelles_MCAP": "159K",
        "X_Factor": "0.9X",
        "PL_Percent": "-11%",
        "PL_Dollar": "-1.12$",
        "Invest": "10"
    },
    {
        "Datum": "27.03.",
        "Symbol": "$Pumpswap ",
        "MCAP_at_Call": "159K",
        "Link": "https://dexscreener.com/solana/fdtu6w24k2iyw9ce9nstyvsmsgjxj2hhrtkkc2xftxsl",
        "Aktuelles_MCAP": "159K",
        "X_Factor": "1.0X",
        "PL_Percent": "0%",
        "PL_Dollar": "0.00$",
        "Invest": "10"
    }
]